nonebot_plugin_emojilike/__init__.py
nonebot_plugin_emojilike/face.py
nonebot_plugin_emojilike-0.2.4.dist-info/WHEEL
nonebot_plugin_emojilike-0.2.4.dist-info/METADATA
nonebot_plugin_emojilike-0.2.4.dist-info/RECORD
