Metadata-Version: 2.3
Name: nonebot-plugin-emojilike
Version: 0.2.4
Summary: nonebot2 名片赞，表情回应插件
Keywords: nonebot,nonebot2,emoji,like
Author: fllesser
Author-email: fllesser <fllessive@gmail.com>
Requires-Dist: emoji>=2.14.1
Requires-Dist: nonebot2>=2.4.2,<3.0.0
Requires-Dist: nonebot-adapter-onebot>=2.4.6
Requires-Dist: nonebot-plugin-localstore>=0.7.3,<1
Requires-Dist: nonebot-plugin-apscheduler>=0.5.0,<1
Requires-Python: >=3.10
Project-URL: Repository, https://github.com/fllesser/nonebot-plugin-emojilike
